pypostalcode/__init__.py
pypostalcode/check_csv.py
pypostalcode/import.py
pypostalcode/postalcodes.db
pypostalcode/settings.py
pypostalcode-0.4.1.dist-info/LICENSE.txt
pypostalcode-0.4.1.dist-info/METADATA
pypostalcode-0.4.1.dist-info/WHEEL
pypostalcode-0.4.1.dist-info/top_level.txt
pypostalcode-0.4.1.dist-info/RECORD
