Metadata-Version: 2.1
Name: pypostalcode
Version: 0.4.1
Summary: Radius searches on Canadian postal codes, location data
Home-page: https://github.com/inkjet/pypostalcode
Author: Scott Rodkey
Author-email: rodkeyscott@gmail.com
License: MIT
Keywords: Canada,postal,code,distance,geonames
Platform: UNKNOWN
License-File: LICENSE.txt
Provides-Extra: dev
Requires-Dist: pytz ; extra == 'dev'
Requires-Dist: timezonefinder ; extra == 'dev'
